MANIFEST.in
README.rst
setup.py
rifle/__init__.py
rifle/checker.py
rifle/constants.py
rifle/errors.py
rifle/main.py
rifle/schemaValidator.py
rifle/utils.py
rifle.egg-info/PKG-INFO
rifle.egg-info/SOURCES.txt
rifle.egg-info/dependency_links.txt
rifle.egg-info/entry_points.txt
rifle.egg-info/requires.txt
rifle.egg-info/top_level.txt
rifle/schemas/schema_isa.yaml
rifle/schemas/schema_platform.yaml